[
    {
        "type": "error",
        "module": "YukkiMusic.platforms.resso",
        "obj": "",
        "line": 17,
        "column": 0,
        "endLine": 17,
        "endColumn": 52,
        "path": "YukkiMusic/platforms/resso.py",
        "symbol": "no-name-in-module",
        "message": "No name 'youtube' in module 'YukkiMusic.core'",
        "message-id": "E0611"
    },
    {
        "type": "error",
        "module": "YukkiMusic.platforms.resso",
        "obj": "Resso.track",
        "line": 46,
        "column": 29,
        "endLine": 46,
        "endColumn": 34,
        "path": "YukkiMusic/platforms/resso.py",
        "symbol": "possibly-used-before-assignment",
        "message": "Possibly using variable 'title' before assignment",
        "message-id": "E0606"
    }
]