[
    {
        "type": "convention",
        "module": "YukkiMusic.utils.inline.song",
        "obj": "",
        "line": 1,
        "column": 0,
        "endLine": null,
        "endColumn": null,
        "path": "YukkiMusic/YukkiMusic/utils/inline/song.py",
        "symbol": "missing-module-docstring",
        "message": "Missing module docstring",
        "message-id": "C0114"
    },
    {
        "type": "error",
        "module": "YukkiMusic.utils.inline.song",
        "obj": "",
        "line": 10,
        "column": 0,
        "endLine": 10,
        "endColumn": 27,
        "path": "YukkiMusic/YukkiMusic/utils/inline/song.py",
        "symbol": "import-error",
        "message": "Unable to import 'telethon'",
        "message-id": "E0401"
    },
    {
        "type": "convention",
        "module": "YukkiMusic.utils.inline.song",
        "obj": "song_markup",
        "line": 13,
        "column": 0,
        "endLine": 13,
        "endColumn": 15,
        "path": "YukkiMusic/YukkiMusic/utils/inline/song.py",
        "symbol": "missing-function-docstring",
        "message": "Missing function or method docstring",
        "message-id": "C0116"
    }
]