[
    {
        "type": "convention",
        "module": "YukkiMusic.plugins.misc.cleanmode",
        "obj": "",
        "line": 1,
        "column": 0,
        "endLine": null,
        "endColumn": null,
        "path": "YM/YukkiMusic/plugins/misc/cleanmode.py",
        "symbol": "missing-module-docstring",
        "message": "Missing module docstring",
        "message-id": "C0114"
    },
    {
        "type": "error",
        "module": "YukkiMusic.plugins.misc.cleanmode",
        "obj": "",
        "line": 14,
        "column": 0,
        "endLine": 14,
        "endColumn": 28,
        "path": "YM/YukkiMusic/plugins/misc/cleanmode.py",
        "symbol": "import-error",
        "message": "Unable to import 'pyrogram'",
        "message-id": "E0401"
    },
    {
        "type": "error",
        "module": "YukkiMusic.plugins.misc.cleanmode",
        "obj": "",
        "line": 15,
        "column": 0,
        "endLine": 15,
        "endColumn": 44,
        "path": "YM/YukkiMusic/plugins/misc/cleanmode.py",
        "symbol": "import-error",
        "message": "Unable to import 'pyrogram.enums'",
        "message-id": "E0401"
    },
    {
        "type": "error",
        "module": "YukkiMusic.plugins.misc.cleanmode",
        "obj": "",
        "line": 16,
        "column": 0,
        "endLine": 16,
        "endColumn": 37,
        "path": "YM/YukkiMusic/plugins/misc/cleanmode.py",
        "symbol": "import-error",
        "message": "Unable to import 'pyrogram.errors'",
        "message-id": "E0401"
    },
    {
        "type": "error",
        "module": "YukkiMusic.plugins.misc.cleanmode",
        "obj": "",
        "line": 17,
        "column": 0,
        "endLine": 17,
        "endColumn": 30,
        "path": "YM/YukkiMusic/plugins/misc/cleanmode.py",
        "symbol": "import-error",
        "message": "Unable to import 'pyrogram.raw'",
        "message-id": "E0401"
    },
    {
        "type": "error",
        "module": "YukkiMusic.plugins.misc.cleanmode",
        "obj": "",
        "line": 21,
        "column": 0,
        "endLine": 21,
        "endColumn": 27,
        "path": "YM/YukkiMusic/plugins/misc/cleanmode.py",
        "symbol": "no-name-in-module",
        "message": "No name 'command' in module 'strings'",
        "message-id": "E0611"
    },
    {
        "type": "convention",
        "module": "YukkiMusic.plugins.misc.cleanmode",
        "obj": "",
        "line": 42,
        "column": 0,
        "endLine": 42,
        "endColumn": 15,
        "path": "YM/YukkiMusic/plugins/misc/cleanmode.py",
        "symbol": "invalid-name",
        "message": "Constant name \"cleanmode_group\" doesn't conform to UPPER_CASE naming style",
        "message-id": "C0103"
    },
    {
        "type": "convention",
        "module": "YukkiMusic.plugins.misc.cleanmode",
        "obj": "clean_mode",
        "line": 46,
        "column": 0,
        "endLine": 46,
        "endColumn": 20,
        "path": "YM/YukkiMusic/plugins/misc/cleanmode.py",
        "symbol": "missing-function-docstring",
        "message": "Missing function or method docstring",
        "message-id": "C0116"
    },
    {
        "type": "warning",
        "module": "YukkiMusic.plugins.misc.cleanmode",
        "obj": "clean_mode",
        "line": 47,
        "column": 4,
        "endLine": 47,
        "endColumn": 26,
        "path": "YM/YukkiMusic/plugins/misc/cleanmode.py",
        "symbol": "global-variable-not-assigned",
        "message": "Using global for 'IS_BROADCASTING' but no assignment is done",
        "message-id": "W0602"
    },
    {
        "type": "warning",
        "module": "YukkiMusic.plugins.misc.cleanmode",
        "obj": "clean_mode",
        "line": 53,
        "column": 11,
        "endLine": 53,
        "endColumn": 20,
        "path": "YM/YukkiMusic/plugins/misc/cleanmode.py",
        "symbol": "broad-exception-caught",
        "message": "Catching too general exception Exception",
        "message-id": "W0718"
    },
    {
        "type": "warning",
        "module": "YukkiMusic.plugins.misc.cleanmode",
        "obj": "clean_mode",
        "line": 46,
        "column": 21,
        "endLine": 46,
        "endColumn": 27,
        "path": "YM/YukkiMusic/plugins/misc/cleanmode.py",
        "symbol": "unused-argument",
        "message": "Unused argument 'client'",
        "message-id": "W0613"
    },
    {
        "type": "convention",
        "module": "YukkiMusic.plugins.misc.cleanmode",
        "obj": "braodcast_message",
        "line": 76,
        "column": 0,
        "endLine": 76,
        "endColumn": 27,
        "path": "YM/YukkiMusic/plugins/misc/cleanmode.py",
        "symbol": "missing-function-docstring",
        "message": "Missing function or method docstring",
        "message-id": "C0116"
    },
    {
        "type": "refactor",
        "module": "YukkiMusic.plugins.misc.cleanmode",
        "obj": "braodcast_message",
        "line": 76,
        "column": 0,
        "endLine": 76,
        "endColumn": 27,
        "path": "YM/YukkiMusic/plugins/misc/cleanmode.py",
        "symbol": "too-many-locals",
        "message": "Too many local variables (23/15)",
        "message-id": "R0914"
    },
    {
        "type": "warning",
        "module": "YukkiMusic.plugins.misc.cleanmode",
        "obj": "braodcast_message",
        "line": 77,
        "column": 4,
        "endLine": 77,
        "endColumn": 26,
        "path": "YM/YukkiMusic/plugins/misc/cleanmode.py",
        "symbol": "global-statement",
        "message": "Using the global statement",
        "message-id": "W0603"
    },
    {
        "type": "warning",
        "module": "YukkiMusic.plugins.misc.cleanmode",
        "obj": "braodcast_message",
        "line": 136,
        "column": 19,
        "endLine": 136,
        "endColumn": 28,
        "path": "YM/YukkiMusic/plugins/misc/cleanmode.py",
        "symbol": "broad-exception-caught",
        "message": "Catching too general exception Exception",
        "message-id": "W0718"
    },
    {
        "type": "error",
        "module": "YukkiMusic.plugins.misc.cleanmode",
        "obj": "braodcast_message",
        "line": 114,
        "column": 50,
        "endLine": 114,
        "endColumn": 51,
        "path": "YM/YukkiMusic/plugins/misc/cleanmode.py",
        "symbol": "possibly-used-before-assignment",
        "message": "Possibly using variable 'y' before assignment",
        "message-id": "E0606"
    },
    {
        "type": "error",
        "module": "YukkiMusic.plugins.misc.cleanmode",
        "obj": "braodcast_message",
        "line": 114,
        "column": 53,
        "endLine": 114,
        "endColumn": 54,
        "path": "YM/YukkiMusic/plugins/misc/cleanmode.py",
        "symbol": "possibly-used-before-assignment",
        "message": "Possibly using variable 'x' before assignment",
        "message-id": "E0606"
    },
    {
        "type": "warning",
        "module": "YukkiMusic.plugins.misc.cleanmode",
        "obj": "braodcast_message",
        "line": 122,
        "column": 27,
        "endLine": 122,
        "endColumn": 36,
        "path": "YM/YukkiMusic/plugins/misc/cleanmode.py",
        "symbol": "broad-exception-caught",
        "message": "Catching too general exception Exception",
        "message-id": "W0718"
    },
    {
        "type": "warning",
        "module": "YukkiMusic.plugins.misc.cleanmode",
        "obj": "braodcast_message",
        "line": 128,
        "column": 27,
        "endLine": 128,
        "endColumn": 36,
        "path": "YM/YukkiMusic/plugins/misc/cleanmode.py",
        "symbol": "broad-exception-caught",
        "message": "Catching too general exception Exception",
        "message-id": "W0718"
    },
    {
        "type": "warning",
        "module": "YukkiMusic.plugins.misc.cleanmode",
        "obj": "braodcast_message",
        "line": 140,
        "column": 15,
        "endLine": 140,
        "endColumn": 24,
        "path": "YM/YukkiMusic/plugins/misc/cleanmode.py",
        "symbol": "broad-exception-caught",
        "message": "Catching too general exception Exception",
        "message-id": "W0718"
    },
    {
        "type": "warning",
        "module": "YukkiMusic.plugins.misc.cleanmode",
        "obj": "braodcast_message",
        "line": 176,
        "column": 19,
        "endLine": 176,
        "endColumn": 28,
        "path": "YM/YukkiMusic/plugins/misc/cleanmode.py",
        "symbol": "broad-exception-caught",
        "message": "Catching too general exception Exception",
        "message-id": "W0718"
    },
    {
        "type": "warning",
        "module": "YukkiMusic.plugins.misc.cleanmode",
        "obj": "braodcast_message",
        "line": 162,
        "column": 27,
        "endLine": 162,
        "endColumn": 36,
        "path": "YM/YukkiMusic/plugins/misc/cleanmode.py",
        "symbol": "broad-exception-caught",
        "message": "Catching too general exception Exception",
        "message-id": "W0718"
    },
    {
        "type": "warning",
        "module": "YukkiMusic.plugins.misc.cleanmode",
        "obj": "braodcast_message",
        "line": 168,
        "column": 27,
        "endLine": 168,
        "endColumn": 36,
        "path": "YM/YukkiMusic/plugins/misc/cleanmode.py",
        "symbol": "broad-exception-caught",
        "message": "Catching too general exception Exception",
        "message-id": "W0718"
    },
    {
        "type": "warning",
        "module": "YukkiMusic.plugins.misc.cleanmode",
        "obj": "braodcast_message",
        "line": 180,
        "column": 15,
        "endLine": 180,
        "endColumn": 24,
        "path": "YM/YukkiMusic/plugins/misc/cleanmode.py",
        "symbol": "broad-exception-caught",
        "message": "Catching too general exception Exception",
        "message-id": "W0718"
    },
    {
        "type": "convention",
        "module": "YukkiMusic.plugins.misc.cleanmode",
        "obj": "braodcast_message",
        "line": 187,
        "column": 8,
        "endLine": 187,
        "endColumn": 54,
        "path": "YM/YukkiMusic/plugins/misc/cleanmode.py",
        "symbol": "import-outside-toplevel",
        "message": "Import outside toplevel (YukkiMusic.core.userbot.assistants)",
        "message-id": "C0415"
    },
    {
        "type": "warning",
        "module": "YukkiMusic.plugins.misc.cleanmode",
        "obj": "braodcast_message",
        "line": 210,
        "column": 23,
        "endLine": 210,
        "endColumn": 32,
        "path": "YM/YukkiMusic/plugins/misc/cleanmode.py",
        "symbol": "broad-exception-caught",
        "message": "Catching too general exception Exception",
        "message-id": "W0718"
    },
    {
        "type": "warning",
        "module": "YukkiMusic.plugins.misc.cleanmode",
        "obj": "braodcast_message",
        "line": 199,
        "column": 20,
        "endLine": 203,
        "endColumn": 21,
        "path": "YM/YukkiMusic/plugins/misc/cleanmode.py",
        "symbol": "expression-not-assigned",
        "message": "Expression \"await client.forward_messages(dialog.chat.id, y, x) if message.reply_to_message else await client.send_message(dialog.chat.id, text=query)\" is assigned to nothing",
        "message-id": "W0106"
    },
    {
        "type": "warning",
        "module": "YukkiMusic.plugins.misc.cleanmode",
        "obj": "braodcast_message",
        "line": 216,
        "column": 15,
        "endLine": 216,
        "endColumn": 24,
        "path": "YM/YukkiMusic/plugins/misc/cleanmode.py",
        "symbol": "broad-exception-caught",
        "message": "Catching too general exception Exception",
        "message-id": "W0718"
    },
    {
        "type": "refactor",
        "module": "YukkiMusic.plugins.misc.cleanmode",
        "obj": "braodcast_message",
        "line": 76,
        "column": 0,
        "endLine": 76,
        "endColumn": 27,
        "path": "YM/YukkiMusic/plugins/misc/cleanmode.py",
        "symbol": "too-many-branches",
        "message": "Too many branches (40/12)",
        "message-id": "R0912"
    },
    {
        "type": "refactor",
        "module": "YukkiMusic.plugins.misc.cleanmode",
        "obj": "braodcast_message",
        "line": 76,
        "column": 0,
        "endLine": 76,
        "endColumn": 27,
        "path": "YM/YukkiMusic/plugins/misc/cleanmode.py",
        "symbol": "too-many-statements",
        "message": "Too many statements (118/50)",
        "message-id": "R0915"
    },
    {
        "type": "convention",
        "module": "YukkiMusic.plugins.misc.cleanmode",
        "obj": "auto_clean",
        "line": 221,
        "column": 0,
        "endLine": 221,
        "endColumn": 20,
        "path": "YM/YukkiMusic/plugins/misc/cleanmode.py",
        "symbol": "missing-function-docstring",
        "message": "Missing function or method docstring",
        "message-id": "C0116"
    },
    {
        "type": "warning",
        "module": "YukkiMusic.plugins.misc.cleanmode",
        "obj": "auto_clean",
        "line": 254,
        "column": 15,
        "endLine": 254,
        "endColumn": 24,
        "path": "YM/YukkiMusic/plugins/misc/cleanmode.py",
        "symbol": "broad-exception-caught",
        "message": "Catching too general exception Exception",
        "message-id": "W0718"
    },
    {
        "type": "convention",
        "module": "YukkiMusic.plugins.misc.cleanmode",
        "obj": "auto_clean",
        "line": 224,
        "column": 12,
        "endLine": 238,
        "endColumn": 77,
        "path": "YM/YukkiMusic/plugins/misc/cleanmode.py",
        "symbol": "consider-using-dict-items",
        "message": "Consider iterating with .items()",
        "message-id": "C0206"
    },
    {
        "type": "convention",
        "module": "YukkiMusic.plugins.misc.cleanmode",
        "obj": "auto_clean",
        "line": 239,
        "column": 12,
        "endLine": 253,
        "endColumn": 71,
        "path": "YM/YukkiMusic/plugins/misc/cleanmode.py",
        "symbol": "consider-using-dict-items",
        "message": "Consider iterating with .items()",
        "message-id": "C0206"
    },
    {
        "type": "warning",
        "module": "YukkiMusic.plugins.misc.cleanmode",
        "obj": "auto_clean",
        "line": 270,
        "column": 15,
        "endLine": 270,
        "endColumn": 24,
        "path": "YM/YukkiMusic/plugins/misc/cleanmode.py",
        "symbol": "broad-exception-caught",
        "message": "Catching too general exception Exception",
        "message-id": "W0718"
    },
    {
        "type": "convention",
        "module": "YukkiMusic.plugins.misc.cleanmode",
        "obj": "auto_clean",
        "line": 257,
        "column": 12,
        "endLine": 269,
        "endColumn": 32,
        "path": "YM/YukkiMusic/plugins/misc/cleanmode.py",
        "symbol": "consider-using-dict-items",
        "message": "Consider iterating with .items()",
        "message-id": "C0206"
    },
    {
        "type": "warning",
        "module": "YukkiMusic.plugins.misc.cleanmode",
        "obj": "auto_clean",
        "line": 266,
        "column": 31,
        "endLine": 266,
        "endColumn": 40,
        "path": "YM/YukkiMusic/plugins/misc/cleanmode.py",
        "symbol": "broad-exception-caught",
        "message": "Catching too general exception Exception",
        "message-id": "W0718"
    },
    {
        "type": "warning",
        "module": "YukkiMusic.plugins.misc.cleanmode",
        "obj": "auto_clean",
        "line": 287,
        "column": 15,
        "endLine": 287,
        "endColumn": 24,
        "path": "YM/YukkiMusic/plugins/misc/cleanmode.py",
        "symbol": "broad-exception-caught",
        "message": "Catching too general exception Exception",
        "message-id": "W0718"
    },
    {
        "type": "refactor",
        "module": "YukkiMusic.plugins.misc.cleanmode",
        "obj": "auto_clean",
        "line": 222,
        "column": 4,
        "endLine": 288,
        "endColumn": 20,
        "path": "YM/YukkiMusic/plugins/misc/cleanmode.py",
        "symbol": "too-many-nested-blocks",
        "message": "Too many nested blocks (6/5)",
        "message-id": "R1702"
    },
    {
        "type": "refactor",
        "module": "YukkiMusic.plugins.misc.cleanmode",
        "obj": "auto_clean",
        "line": 221,
        "column": 0,
        "endLine": 221,
        "endColumn": 20,
        "path": "YM/YukkiMusic/plugins/misc/cleanmode.py",
        "symbol": "too-many-branches",
        "message": "Too many branches (23/12)",
        "message-id": "R0912"
    },
    {
        "type": "refactor",
        "module": "YukkiMusic.plugins.misc.cleanmode",
        "obj": "auto_clean",
        "line": 221,
        "column": 0,
        "endLine": 221,
        "endColumn": 20,
        "path": "YM/YukkiMusic/plugins/misc/cleanmode.py",
        "symbol": "too-many-statements",
        "message": "Too many statements (58/50)",
        "message-id": "R0915"
    }
]