[
    {
        "type": "convention",
        "module": "YukkiMusic.plugins.tools.songs",
        "obj": "songs_back_helper",
        "line": 150,
        "column": 36,
        "endLine": 150,
        "endColumn": 49,
        "path": "YukkiMusic/plugins/tools/songs.py",
        "symbol": "invalid-name",
        "message": "Argument name \"CallbackQuery\" doesn't conform to snake_case naming style",
        "message-id": "C0103"
    },
    {
        "type": "convention",
        "module": "YukkiMusic.plugins.tools.songs",
        "obj": "song_helper_cb",
        "line": 167,
        "column": 33,
        "endLine": 167,
        "endColumn": 46,
        "path": "YukkiMusic/plugins/tools/songs.py",
        "symbol": "invalid-name",
        "message": "Argument name \"CallbackQuery\" doesn't conform to snake_case naming style",
        "message-id": "C0103"
    },
    {
        "type": "convention",
        "module": "YukkiMusic.plugins.tools.songs",
        "obj": "song_download_cb",
        "line": 297,
        "column": 35,
        "endLine": 297,
        "endColumn": 48,
        "path": "YukkiMusic/plugins/tools/songs.py",
        "symbol": "invalid-name",
        "message": "Argument name \"CallbackQuery\" doesn't conform to snake_case naming style",
        "message-id": "C0103"
    },
    {
        "type": "error",
        "module": "YukkiMusic.plugins.tools.songs",
        "obj": "",
        "line": 30,
        "column": 0,
        "endLine": 30,
        "endColumn": 27,
        "path": "YukkiMusic/plugins/tools/songs.py",
        "symbol": "no-name-in-module",
        "message": "No name 'command' in module 'strings'",
        "message-id": "E0611"
    },
    {
        "type": "error",
        "module": "YukkiMusic.plugins.tools.songs",
        "obj": "",
        "line": 31,
        "column": 0,
        "endLine": 31,
        "endColumn": 36,
        "path": "YukkiMusic/plugins/tools/songs.py",
        "symbol": "no-name-in-module",
        "message": "No name 'Platform' in module 'YukkiMusic'",
        "message-id": "E0611"
    },
    {
        "type": "error",
        "module": "YukkiMusic.plugins.tools.songs",
        "obj": "",
        "line": 32,
        "column": 0,
        "endLine": 32,
        "endColumn": 48,
        "path": "YukkiMusic/plugins/tools/songs.py",
        "symbol": "no-name-in-module",
        "message": "No name 'Youtube' in module 'YukkiMusic.platforms'",
        "message-id": "E0611"
    },
    {
        "type": "error",
        "module": "YukkiMusic.plugins.tools.songs",
        "obj": "song_commad_group",
        "line": 53,
        "column": 10,
        "endLine": 53,
        "endColumn": 15,
        "path": "YukkiMusic/plugins/tools/songs.py",
        "symbol": "undefined-variable",
        "message": "Undefined variable 'event'",
        "message-id": "E0602"
    },
    {
        "type": "error",
        "module": "YukkiMusic.plugins.tools.songs",
        "obj": "song_commad_private",
        "line": 71,
        "column": 25,
        "endLine": 71,
        "endColumn": 30,
        "path": "YukkiMusic/plugins/tools/songs.py",
        "symbol": "undefined-variable",
        "message": "Undefined variable 'event'",
        "message-id": "E0602"
    },
    {
        "type": "error",
        "module": "YukkiMusic.plugins.tools.songs",
        "obj": "song_commad_private",
        "line": 73,
        "column": 23,
        "endLine": 73,
        "endColumn": 28,
        "path": "YukkiMusic/plugins/tools/songs.py",
        "symbol": "undefined-variable",
        "message": "Undefined variable 'event'",
        "message-id": "E0602"
    },
    {
        "type": "error",
        "module": "YukkiMusic.plugins.tools.songs",
        "obj": "song_commad_private",
        "line": 107,
        "column": 25,
        "endLine": 107,
        "endColumn": 30,
        "path": "YukkiMusic/plugins/tools/songs.py",
        "symbol": "undefined-variable",
        "message": "Undefined variable 'event'",
        "message-id": "E0602"
    },
    {
        "type": "error",
        "module": "YukkiMusic.plugins.tools.songs",
        "obj": "song_commad_private",
        "line": 109,
        "column": 19,
        "endLine": 109,
        "endColumn": 24,
        "path": "YukkiMusic/plugins/tools/songs.py",
        "symbol": "undefined-variable",
        "message": "Undefined variable 'event'",
        "message-id": "E0602"
    },
    {
        "type": "refactor",
        "module": "YukkiMusic.plugins.tools.songs",
        "obj": "song_commad_private",
        "line": 67,
        "column": 4,
        "endLine": 107,
        "endColumn": 49,
        "path": "YukkiMusic/plugins/tools/songs.py",
        "symbol": "no-else-return",
        "message": "Unnecessary \"else\" after \"return\", remove the \"else\" and de-indent the code inside it",
        "message-id": "R1705"
    },
    {
        "type": "refactor",
        "module": "YukkiMusic.plugins.tools.songs",
        "obj": "song_commad_private",
        "line": 61,
        "column": 0,
        "endLine": 61,
        "endColumn": 29,
        "path": "YukkiMusic/plugins/tools/songs.py",
        "symbol": "too-many-return-statements",
        "message": "Too many return statements (9/6)",
        "message-id": "R0911"
    },
    {
        "type": "refactor",
        "module": "YukkiMusic.plugins.tools.songs",
        "obj": "song_helper_cb",
        "line": 167,
        "column": 0,
        "endLine": 167,
        "endColumn": 24,
        "path": "YukkiMusic/plugins/tools/songs.py",
        "symbol": "too-many-locals",
        "message": "Too many local variables (17/15)",
        "message-id": "R0914"
    },
    {
        "type": "refactor",
        "module": "YukkiMusic.plugins.tools.songs",
        "obj": "song_helper_cb",
        "line": 183,
        "column": 4,
        "endLine": 289,
        "endColumn": 78,
        "path": "YukkiMusic/plugins/tools/songs.py",
        "symbol": "no-else-return",
        "message": "Unnecessary \"else\" after \"return\", remove the \"else\" and de-indent the code inside it",
        "message-id": "R1705"
    },
    {
        "type": "refactor",
        "module": "YukkiMusic.plugins.tools.songs",
        "obj": "song_helper_cb",
        "line": 167,
        "column": 0,
        "endLine": 167,
        "endColumn": 24,
        "path": "YukkiMusic/plugins/tools/songs.py",
        "symbol": "too-many-branches",
        "message": "Too many branches (13/12)",
        "message-id": "R0912"
    },
    {
        "type": "refactor",
        "module": "YukkiMusic.plugins.tools.songs",
        "obj": "song_download_cb",
        "line": 297,
        "column": 0,
        "endLine": 297,
        "endColumn": 26,
        "path": "YukkiMusic/plugins/tools/songs.py",
        "symbol": "too-many-locals",
        "message": "Too many local variables (19/15)",
        "message-id": "R0914"
    },
    {
        "type": "warning",
        "module": "YukkiMusic.plugins.tools.songs",
        "obj": "song_commad_group",
        "line": 40,
        "column": 28,
        "endLine": 40,
        "endColumn": 34,
        "path": "YukkiMusic/plugins/tools/songs.py",
        "symbol": "unused-argument",
        "message": "Unused argument 'client'",
        "message-id": "W0613"
    },
    {
        "type": "warning",
        "module": "YukkiMusic.plugins.tools.songs",
        "obj": "song_commad_group",
        "line": 40,
        "column": 36,
        "endLine": 40,
        "endColumn": 52,
        "path": "YukkiMusic/plugins/tools/songs.py",
        "symbol": "unused-argument",
        "message": "Unused argument 'message'",
        "message-id": "W0613"
    },
    {
        "type": "warning",
        "module": "YukkiMusic.plugins.tools.songs",
        "obj": "song_commad_private",
        "line": 123,
        "column": 11,
        "endLine": 123,
        "endColumn": 20,
        "path": "YukkiMusic/plugins/tools/songs.py",
        "symbol": "broad-exception-caught",
        "message": "Catching too general exception Exception",
        "message-id": "W0718"
    },
    {
        "type": "warning",
        "module": "YukkiMusic.plugins.tools.songs",
        "obj": "song_commad_private",
        "line": 61,
        "column": 30,
        "endLine": 61,
        "endColumn": 36,
        "path": "YukkiMusic/plugins/tools/songs.py",
        "symbol": "unused-argument",
        "message": "Unused argument 'client'",
        "message-id": "W0613"
    },
    {
        "type": "warning",
        "module": "YukkiMusic.plugins.tools.songs",
        "obj": "songs_back_helper",
        "line": 150,
        "column": 28,
        "endLine": 150,
        "endColumn": 34,
        "path": "YukkiMusic/plugins/tools/songs.py",
        "symbol": "unused-argument",
        "message": "Unused argument 'client'",
        "message-id": "W0613"
    },
    {
        "type": "warning",
        "module": "YukkiMusic.plugins.tools.songs",
        "obj": "songs_back_helper",
        "line": 156,
        "column": 4,
        "endLine": 156,
        "endColumn": 9,
        "path": "YukkiMusic/plugins/tools/songs.py",
        "symbol": "unused-variable",
        "message": "Unused variable 'stype'",
        "message-id": "W0612"
    },
    {
        "type": "warning",
        "module": "YukkiMusic.plugins.tools.songs",
        "obj": "song_helper_cb",
        "line": 179,
        "column": 11,
        "endLine": 179,
        "endColumn": 20,
        "path": "YukkiMusic/plugins/tools/songs.py",
        "symbol": "broad-exception-caught",
        "message": "Catching too general exception Exception",
        "message-id": "W0718"
    },
    {
        "type": "warning",
        "module": "YukkiMusic.plugins.tools.songs",
        "obj": "song_helper_cb",
        "line": 189,
        "column": 15,
        "endLine": 189,
        "endColumn": 24,
        "path": "YukkiMusic/plugins/tools/songs.py",
        "symbol": "broad-exception-caught",
        "message": "Catching too general exception Exception",
        "message-id": "W0718"
    },
    {
        "type": "warning",
        "module": "YukkiMusic.plugins.tools.songs",
        "obj": "song_helper_cb",
        "line": 233,
        "column": 71,
        "endLine": 233,
        "endColumn": 79,
        "path": "YukkiMusic/plugins/tools/songs.py",
        "symbol": "f-string-without-interpolation",
        "message": "Using an f-string that does not have any interpolated variables",
        "message-id": "W1309"
    },
    {
        "type": "warning",
        "module": "YukkiMusic.plugins.tools.songs",
        "obj": "song_helper_cb",
        "line": 244,
        "column": 15,
        "endLine": 244,
        "endColumn": 24,
        "path": "YukkiMusic/plugins/tools/songs.py",
        "symbol": "broad-exception-caught",
        "message": "Catching too general exception Exception",
        "message-id": "W0718"
    },
    {
        "type": "warning",
        "module": "YukkiMusic.plugins.tools.songs",
        "obj": "song_helper_cb",
        "line": 286,
        "column": 71,
        "endLine": 286,
        "endColumn": 79,
        "path": "YukkiMusic/plugins/tools/songs.py",
        "symbol": "f-string-without-interpolation",
        "message": "Using an f-string that does not have any interpolated variables",
        "message-id": "W1309"
    },
    {
        "type": "warning",
        "module": "YukkiMusic.plugins.tools.songs",
        "obj": "song_helper_cb",
        "line": 187,
        "column": 31,
        "endLine": 187,
        "endColumn": 35,
        "path": "YukkiMusic/plugins/tools/songs.py",
        "symbol": "unused-variable",
        "message": "Unused variable 'link'",
        "message-id": "W0612"
    },
    {
        "type": "warning",
        "module": "YukkiMusic.plugins.tools.songs",
        "obj": "song_download_cb",
        "line": 303,
        "column": 11,
        "endLine": 303,
        "endColumn": 20,
        "path": "YukkiMusic/plugins/tools/songs.py",
        "symbol": "broad-exception-caught",
        "message": "Catching too general exception Exception",
        "message-id": "W0718"
    },
    {
        "type": "warning",
        "module": "YukkiMusic.plugins.tools.songs",
        "obj": "song_download_cb",
        "line": 347,
        "column": 15,
        "endLine": 347,
        "endColumn": 24,
        "path": "YukkiMusic/plugins/tools/songs.py",
        "symbol": "broad-exception-caught",
        "message": "Catching too general exception Exception",
        "message-id": "W0718"
    },
    {
        "type": "warning",
        "module": "YukkiMusic.plugins.tools.songs",
        "obj": "song_download_cb",
        "line": 372,
        "column": 15,
        "endLine": 372,
        "endColumn": 24,
        "path": "YukkiMusic/plugins/tools/songs.py",
        "symbol": "broad-exception-caught",
        "message": "Catching too general exception Exception",
        "message-id": "W0718"
    },
    {
        "type": "warning",
        "module": "YukkiMusic.plugins.tools.songs",
        "obj": "song_download_cb",
        "line": 392,
        "column": 15,
        "endLine": 392,
        "endColumn": 24,
        "path": "YukkiMusic/plugins/tools/songs.py",
        "symbol": "broad-exception-caught",
        "message": "Catching too general exception Exception",
        "message-id": "W0718"
    },
    {
        "type": "warning",
        "module": "YukkiMusic.plugins.tools.songs",
        "obj": "song_download_cb",
        "line": 415,
        "column": 15,
        "endLine": 415,
        "endColumn": 24,
        "path": "YukkiMusic/plugins/tools/songs.py",
        "symbol": "broad-exception-caught",
        "message": "Catching too general exception Exception",
        "message-id": "W0718"
    }
]